<nationality_menu>
    <nationality_node><id>01</id><value>阿昌</value></nationality_node>
    <nationality_node><id>02</id><value>白</value></nationality_node>
    <nationality_node><id>03</id><value>保安</value></nationality_node>
    <nationality_node><id>04</id><value>布朗</value></nationality_node>
    <nationality_node><id>05</id><value>布依</value></nationality_node>
    <nationality_node><id>06</id><value>藏</value></nationality_node>
    <nationality_node><id>07</id><value>朝鲜</value></nationality_node>
    <nationality_node><id>08</id><value>达斡尔</value></nationality_node>
    <nationality_node><id>09</id><value>傣</value></nationality_node>
    <nationality_node><id>10</id><value>德昂</value></nationality_node>
    <nationality_node><id>11</id><value>东乡</value></nationality_node>
    <nationality_node><id>12</id><value>侗</value></nationality_node>
    <nationality_node><id>13</id><value>独龙</value></nationality_node>
    <nationality_node><id>14</id><value>俄罗斯</value></nationality_node>
    <nationality_node><id>15</id><value>鄂伦春</value></nationality_node>
    <nationality_node><id>16</id><value>鄂温克</value></nationality_node>
    <nationality_node><id>17</id><value>高山</value></nationality_node>
    <nationality_node><id>18</id><value>哈尼</value></nationality_node>
    <nationality_node><id>19</id><value>哈萨克</value></nationality_node>
    <nationality_node><id>20</id><value>汉</value></nationality_node>
    <nationality_node><id>21</id><value>赫哲</value></nationality_node>
    <nationality_node><id>22</id><value>回</value></nationality_node>
    <nationality_node><id>23</id><value>基诺</value></nationality_node>
    <nationality_node><id>24</id><value>京</value></nationality_node>
    <nationality_node><id>25</id><value>景颇</value></nationality_node>
    <nationality_node><id>26</id><value>柯尔克孜</value></nationality_node>
    <nationality_node><id>27</id><value>拉祜</value></nationality_node>
    <nationality_node><id>28</id><value>黎</value></nationality_node>
    <nationality_node><id>29</id><value>傈僳</value></nationality_node>
    <nationality_node><id>30</id><value>珞巴</value></nationality_node>
    <nationality_node><id>31</id><value>满</value></nationality_node>
    <nationality_node><id>32</id><value>毛南</value></nationality_node>
    <nationality_node><id>33</id><value>门巴</value></nationality_node>
    <nationality_node><id>34</id><value>蒙古</value></nationality_node>
    <nationality_node><id>35</id><value>苗</value></nationality_node>
    <nationality_node><id>36</id><value>仫佬</value></nationality_node>
    <nationality_node><id>37</id><value>纳西</value></nationality_node>
    <nationality_node><id>38</id><value>怒</value></nationality_node>
    <nationality_node><id>39</id><value>普米</value></nationality_node>
    <nationality_node><id>40</id><value>羌</value></nationality_node>
    <nationality_node><id>41</id><value>撒拉</value></nationality_node>
    <nationality_node><id>42</id><value>畲</value></nationality_node>
    <nationality_node><id>43</id><value>水</value></nationality_node>
    <nationality_node><id>44</id><value>塔吉克</value></nationality_node>
    <nationality_node><id>45</id><value>塔塔尔</value></nationality_node>
    <nationality_node><id>46</id><value>土家</value></nationality_node>
    <nationality_node><id>47</id><value>土</value></nationality_node>
    <nationality_node><id>48</id><value>佤</value></nationality_node>
    <nationality_node><id>49</id><value>维吾尔</value></nationality_node>
    <nationality_node><id>50</id><value>乌孜别克</value></nationality_node>
    <nationality_node><id>51</id><value>锡伯</value></nationality_node>
    <nationality_node><id>52</id><value>瑶</value></nationality_node>
    <nationality_node><id>53</id><value>彝</value></nationality_node>
    <nationality_node><id>54</id><value>仡佬</value></nationality_node>
    <nationality_node><id>55</id><value>裕固</value></nationality_node>
    <nationality_node><id>56</id><value>壮</value></nationality_node>
</nationality_menu>